funcutils/__init__.py
funcutils/funcutils.py
j_funcutils-0.0.7.dist-info/LICENSE
j_funcutils-0.0.7.dist-info/METADATA
j_funcutils-0.0.7.dist-info/WHEEL
j_funcutils-0.0.7.dist-info/top_level.txt
j_funcutils-0.0.7.dist-info/RECORD
