Metadata-Version: 2.1
Name: j-funcutils
Version: 0.0.7
Summary: A basic cost time calculator
Home-page: https://github.com/juanmacaaz/FuncUtils
Author: Juan Manuel Camara Diaz
Author-email: juanma.caaz@gmail.com
License: UNKNOWN
Platform: UNKNOWN
Classifier: Programming Language :: Python :: 3
Classifier: License :: OSI Approved :: MIT License
Classifier: Operating System :: OS Independent
